acrud/__init__.py
acrud/exception.py
acrud/settings.py
acrud/storage/__init__.py
acrud/storage/base.py
acrud/storage/convert.py
acrud/storage/google_drive/__init__.py
acrud/storage/google_drive/google_drive.py
acrud/storage/local/__init__.py
acrud/storage/local/local.py
acrud/storage/s3/__init__.py
acrud/storage/s3/s3.py
acrud/storage/s3_tmp/__init__.py
acrud/storage/s3_tmp/s3_tmp.py
acrud/storage/utils.py
acrud-0.4.2.dist-info/METADATA
acrud-0.4.2.dist-info/WHEEL
acrud-0.4.2.dist-info/RECORD
