Metadata-Version: 2.3
Name: acrud
Version: 0.4.2
Summary: 
Author: jacantwell
Author-email: jasper66018@gmail.com
Requires-Python: >=3.10,<3.13
Classifier: Programming Language :: Python :: 3
Classifier: Programming Language :: Python :: 3.10
Classifier: Programming Language :: Python :: 3.11
Classifier: Programming Language :: Python :: 3.12
Provides-Extra: gdrive
Provides-Extra: s3
Requires-Dist: boto3 (>=1.34.143,<2.0.0) ; extra == "s3"
Requires-Dist: dill (>=0.3.8,<0.4.0)
Requires-Dist: google-api-python-client (>=2.154.0,<3.0.0) ; extra == "gdrive"
Requires-Dist: google-auth-httplib2 (>=0.2.0,<0.3.0) ; extra == "gdrive"
Requires-Dist: google-auth-oauthlib (>=1.2.1,<2.0.0) ; extra == "gdrive"
Requires-Dist: multimethod (>=1.12,<2.0)
Requires-Dist: mypy-boto3-s3 (>=1.37.0,<2.0.0) ; extra == "s3"
Requires-Dist: pydantic (>=2.9.2,<3.0.0)
Requires-Dist: pypdf2 (>=3.0.1,<4.0.0)
Requires-Dist: pytest (>=8.2.2,<9.0.0)
Requires-Dist: python-dotenv (>=1.0.1,<2.0.0)
Requires-Dist: stringcase (>=1.2.0,<2.0.0)
Requires-Dist: typeguard (>=2.13.3)
